virtual_touchpad-0.19.1.dist-info/DESCRIPTION.rst
virtual_touchpad-0.19.1.dist-info/METADATA
virtual_touchpad-0.19.1.dist-info/RECORD
virtual_touchpad-0.19.1.dist-info/WHEEL
virtual_touchpad-0.19.1.dist-info/metadata.json
virtual_touchpad-0.19.1.dist-info/top_level.txt
virtual_touchpad-0.19.1.dist-info/zip-safe
virtualtouchpad/__init__.py
virtualtouchpad/__main__.py
virtualtouchpad/_info.py
virtualtouchpad/icon-dark.png
virtualtouchpad/icon-light.png
virtualtouchpad/notifier.py
virtualtouchpad/resource.py
virtualtouchpad/status.py
virtualtouchpad/store.py
virtualtouchpad/translation.py
virtualtouchpad/trayicon.py
virtualtouchpad/value.py
virtualtouchpad/configuration/__init__.py
virtualtouchpad/configuration/notifier.py
virtualtouchpad/dispatchers/__init__.py
virtualtouchpad/dispatchers/keyboard.py
virtualtouchpad/dispatchers/mouse.py
virtualtouchpad/html/favicon.ico
virtualtouchpad/html/favicon.png
virtualtouchpad/html/index.xhtml
virtualtouchpad/html/index.xhtml.min
virtualtouchpad/html/virtual-touchpad.appcache
virtualtouchpad/html/css/app.css
virtualtouchpad/html/css/doc.css
virtualtouchpad/html/css/help.css
virtualtouchpad/html/css/keyboard.css
virtualtouchpad/html/css/message-box.css
virtualtouchpad/html/css/qr.css
virtualtouchpad/html/css/touchpad.css
virtualtouchpad/html/css/trackbar.css
virtualtouchpad/html/help/index.xhtml
virtualtouchpad/html/help/index.xhtml.min
virtualtouchpad/html/img/fullscreen.svg
virtualtouchpad/html/img/help.svg
virtualtouchpad/html/img/icon114x114.png
virtualtouchpad/html/img/icon144x144.png
virtualtouchpad/html/img/icon196x196.png
virtualtouchpad/html/img/icon57x57.png
virtualtouchpad/html/img/icon72x72.png
virtualtouchpad/html/img/settings.svg
virtualtouchpad/html/js/app.js
virtualtouchpad/html/js/qr.js
virtualtouchpad/html/js/lib/checks.js
virtualtouchpad/html/js/lib/configuration.js
virtualtouchpad/html/js/lib/controller.js
virtualtouchpad/html/js/lib/features.js
virtualtouchpad/html/js/lib/include.js
virtualtouchpad/html/js/lib/init.js
virtualtouchpad/html/js/lib/keyboard.js
virtualtouchpad/html/js/lib/message-box.js
virtualtouchpad/html/js/lib/server.js
virtualtouchpad/html/js/lib/template.js
virtualtouchpad/html/js/lib/trackbar.js
virtualtouchpad/html/js/lib/translation.js
