Metadata-Version: 2.0
Name: virtual-touchpad
Version: 0.19.1
Summary: Turns your mobile or tablet into a touchpad and keyboard for your computer.
Home-page: https://github.com/moses-palmer/virtual-touchpad
Author: Moses Palmér
Author-email: moses.palmer@gmail.com
License: GPLv3
Keywords: control mouse,control keyboard
Platform: linux
Platform: windows
Classifier: Development Status :: 4 - Beta
Classifier: Intended Audience :: End Users/Desktop
Classifier: License :: OSI Approved :: GNU General Public License v3 (GPLv3)
Classifier: Operating System :: MacOS :: MacOS X
Classifier: Operating System :: Microsoft :: Windows :: Windows NT/2000
Classifier: Operating System :: POSIX
Classifier: Programming Language :: Python
Classifier: Programming Language :: Python :: 3.5
Requires-Dist: aiohttp (>=1.2)
Requires-Dist: netifaces (>=0.8)
Requires-Dist: Pillow (>=1.1.7)
Requires-Dist: pynput (>=1.1.3)
Requires-Dist: pyqrcode (>=1.2.1)
Requires-Dist: pystray (>=0.11)
Requires-Dist: zeroconf (>=0.17)
